xvector_jtubespeech/__init__.py
xvector_jtubespeech/network/__init__.py
xvector_jtubespeech/network/tdnn.py
xvector_jtubespeech/network/xvector.py
xvector_jtubespeech-0.0.2.dist-info/METADATA
xvector_jtubespeech-0.0.2.dist-info/WHEEL
xvector_jtubespeech-0.0.2.dist-info/licenses/LICENSE
xvector_jtubespeech-0.0.2.dist-info/RECORD
