Metadata-Version: 2.1
Name: xvector_jtubespeech
Version: 0.0.2
Summary: Pre-trained model for extracting the x-vector (speaker representation vector)
License-File: LICENSE
Requires-Python: >=3.8
Requires-Dist: numpy>=1.22.3
Requires-Dist: scipy>=1.8.0
Requires-Dist: torch>=1.10.2
Requires-Dist: torchaudio>=0.10.2
